rmt_audio-0.3.1.dist-info/METADATA
rmt_audio-0.3.1.dist-info/WHEEL
rmt_audio-0.3.1.dist-info/entry_points.txt
rmt_audio-0.3.1.dist-info/licenses/LICENSE
rmt_audio/__init__.py
rmt_audio/remote.py
rmt_audio-0.3.1.dist-info/RECORD
