Metadata-Version: 2.1
Name: RMT-Audio
Version: 0.3.1
Summary: Default template for PDM package
Author-Email: khr0106 <kanghr990106@gmail.com>
License: MIT
Requires-Python: >=3.10
Requires-Dist: pytest>=8.3.4
Requires-Dist: pandas>=2.2.3
